README.md
setup.py
confi/__init__.py
confi/confi.py
confi.egg-info/PKG-INFO
confi.egg-info/SOURCES.txt
confi.egg-info/dependency_links.txt
confi.egg-info/requires.txt
confi.egg-info/top_level.txt