Metadata-Version: 2.1
Name: confi
Version: 0.0.4.1
Summary: Comfortable python app configuration
Home-page: UNKNOWN
Author: Boris Tseitlin
Author-email: btseytlin@start.film
License: UNKNOWN
Keywords: configuration,env,docker
Platform: UNKNOWN
Provides-Extra: test
